viterbi.py
viterbicodec.cp312-win_amd64.pyd
viterbi-0.0.6.dist-info/licenses/LICENSE
viterbi-0.0.6.dist-info/licenses/NOTICE
viterbi-0.0.6.dist-info/METADATA
viterbi-0.0.6.dist-info/WHEEL
viterbi-0.0.6.dist-info/top_level.txt
viterbi-0.0.6.dist-info/RECORD
