Metadata-Version: 2.1
Name: viterbi
Version: 0.0.6
Summary: A Convolutional Encoder and Viterbi Decoder in Python/C++.
Author-email: Yachen Mao <maoyachen55@gmail.com>, Min Xu <xukmin@gmail.com>
License: Apache License
Project-URL: Source, https://github.com/clysto/viterbi
Keywords: viterbi
Classifier: Programming Language :: C++
Classifier: Programming Language :: Python
Classifier: Programming Language :: Python :: 3
Classifier: Programming Language :: Python :: 3 :: Only
Classifier: Programming Language :: Python :: 3.7
Classifier: Programming Language :: Python :: 3.8
Classifier: Programming Language :: Python :: 3.9
Classifier: Programming Language :: Python :: 3.10
Classifier: Programming Language :: Python :: 3.11
Classifier: Programming Language :: Python :: 3.12
Classifier: Programming Language :: Python :: 3.13
Classifier: Programming Language :: Python :: 3.14
Requires-Python: >=3.7
License-File: LICENSE
License-File: NOTICE
